fabrique_kafka_kv/__init__.py
fabrique_kafka_kv/kafka_admin.py
fabrique_kafka_kv/kafka_compaction.py
fabrique_kafka_kv/kafka_db.py
fabrique_kafka_kv-2021.1.5.1.dist-info/METADATA
fabrique_kafka_kv-2021.1.5.1.dist-info/WHEEL
fabrique_kafka_kv-2021.1.5.1.dist-info/top_level.txt
fabrique_kafka_kv-2021.1.5.1.dist-info/RECORD
